ymrp/__init__.py
ymrp/constants.py
ymrp/parser.py
ymrp-0.6.0.dist-info/licenses/LICENSE
ymrp-0.6.0.dist-info/METADATA
ymrp-0.6.0.dist-info/WHEEL
ymrp-0.6.0.dist-info/top_level.txt
ymrp-0.6.0.dist-info/RECORD
