Metadata-Version: 2.4
Name: ymrp
Version: 0.6.0
Summary: Yandex map resources parser library
Author-email: Miron <berchetov@gmail.com>
License-Expression: Apache-2.0
Requires-Python: >=3.12
License-File: LICENSE
Requires-Dist: beautifulsoup4>=4.13.4
Requires-Dist: playwright>=1.53.0
Dynamic: license-file
